solarkit/__init__.py
solarkit/planet.py
solarkit/solar_system.py
solarkit/utils.py
solarkit/viewer.py
solarkit-1.0.1.dist-info/LICENSE
solarkit-1.0.1.dist-info/METADATA
solarkit-1.0.1.dist-info/WHEEL
solarkit-1.0.1.dist-info/top_level.txt
solarkit-1.0.1.dist-info/RECORD
