Metadata-Version: 2.1
Name: solarkit
Version: 1.0.1
Summary: Visualise a solar system and do cool stuff with it
Author: Carlos Lorenzo
Author-email: <clorenzozuniga@gmail.com>
Keywords: solar system,space,astrophysics,bpho
Classifier: Development Status :: 4 - Beta
Classifier: Intended Audience :: Education
Classifier: Programming Language :: Python :: 3
Classifier: Operating System :: Unix
Classifier: Operating System :: MacOS :: MacOS X
Classifier: Operating System :: Microsoft :: Windows
License-File: LICENSE
Requires-Dist: numpy
Requires-Dist: pandas
Requires-Dist: matplotlib
Requires-Dist: scipy
